{"name": "Лепешки из творога и картофеля", "Калорийность": 153.8, "Белки": 9.3, "Жиры": 8.9, "Углеводы": 9.9, "Органические кислоты": 20.7, "Пищевые волокна": 1.1, "Вода": 61.0, "Зола": 1.0, "Витамин А": 100.0, "Ретинол": 0.1, "Витамин В1": 0.07, "Витамин В2": 0.1, "Витамин В4": 25.8, "Витамин В5": 0.2, "Витамин В6": 0.1, "Витамин В9": 5.3, "Витамин В12": 0.05, "Витамин C": 5.1, "Витамин D": 0.2, "Витамин Е": 0.3, "Витамин Н": 1.7, "Витамин РР": 2.1438, "Ниацин": 0.6, "Калий": 221.4, "Кальций": 75.4, "Кремний": 0.3, "Магний": 17.9, "Натрий": 20.9, "Сера": 19.5, "Фосфор": 120.8, "Хлор": 332.4, "Алюминий": 312.5, "Бор": 34.0, "Ванадий": 47.2, "Железо": 0.7, "Йод": 2.4, "Кобальт": 2.2, "Литий": 20.9, "Марганец": 0.0923, "Медь": 50.9, "Молибден": 4.0, "Никель": 1.5, "Олово": 0.4, "Рубидий": 135.9, "Селен": 0.5, "Титан": 0.8, "Фтор": 9.8, "Хром": 3.1, "Цинк": 0.2438, "Крахмал и декстрины": 7.9, "Моно- и дисахариды (сахара)": 1.6, "Холестерин": 10.6}